load_envfile/__init__.py
load_envfile/load_envfile.py
load_envfile-0.5.dist-info/METADATA
load_envfile-0.5.dist-info/WHEEL
load_envfile-0.5.dist-info/top_level.txt
load_envfile-0.5.dist-info/RECORD
